redis_cache/__init__.py
redis_cache/rediscache.py
redis_cache_tools-1.1.1.dist-info/WHEEL
redis_cache_tools-1.1.1.dist-info/METADATA
redis_cache_tools-1.1.1.dist-info/RECORD
