Metadata-Version: 2.1
Name: redis-cache-tools
Version: 1.1.1
Summary: redis-cache-tools is a pythonic interface for creating a cache over redis.
Home-page: https://500apps.com
Keywords: redis-cache-tools
Author: It provides simple decorators that can be added to any function to cache its return values.
Requires-Python: >=3.8,<4.0
Classifier: Operating System :: OS Independent
Classifier: Programming Language :: Python :: 3
Classifier: Programming Language :: Python :: 3.8
Classifier: Programming Language :: Python :: 3.9
Classifier: Programming Language :: Python :: 3.10
Classifier: Topic :: Software Development :: Documentation
Classifier: Topic :: Software Development :: Libraries :: Python Modules
Classifier: Topic :: Software Development :: Quality Assurance
Requires-Dist: redis (>=4.0.0)
Project-URL: Repository, https://500apps.com
